[{"id":74,"name":"Saints and Sinners AC","active":true,"type":"club","description":"Lifestyle Night Club","roomId":"saints-and-sinners-ac","agreement":null,"reset":false,"allowTranscoding":null,"recording":false,"recordingMode":null,"map_sessions":null,"analytics":null,"liveStream":false,"shortName":null,"created_at":"2022-06-03T17:55:49.508Z","updated_at":"2022-06-03T17:55:49.514Z","forceVideoCodec":null,"forcedVideoCodec":null,"defaultRecordingProperties":null,"connections":[]},{"id":4,"name":"Hot wife","active":true,"type":"public","description":null,"roomId":"hot-wife","agreement":null,"reset":false,"allowTranscoding":null,"recording":false,"recordingMode":null,"map_sessions":null,"analytics":null,"liveStream":false,"shortName":null,"created_at":"2022-06-01T14:13:14.955Z","updated_at":"2022-06-01T14:13:14.959Z","forceVideoCodec":null,"forcedVideoCodec":null,"defaultRecordingProperties":null,"connections":[]}]